cleanplots/__init__.py
cleanplots/_version.py
cleanplots/cleanplots.py
prettyplots/__init__.py
prettyplots/_version.py
prettyplots/prettyplots.py
cleanplots-0.2.2.dist-info/LICENSE
cleanplots-0.2.2.dist-info/METADATA
cleanplots-0.2.2.dist-info/WHEEL
cleanplots-0.2.2.dist-info/top_level.txt
cleanplots-0.2.2.dist-info/RECORD
