Metadata-Version: 2.1
Name: cleanplots
Version: 0.2.2
Summary: Nice looking MPL plots
Home-page: https://github.com/henrypinkard/cleanplots
Author: Henry Pinkard
Author-email: henry.pinkard@gmail.com
Classifier: Programming Language :: Python :: 3.6
Classifier: Programming Language :: Python :: 3.7
Classifier: Programming Language :: Python :: 3.8
Classifier: Development Status :: 3 - Alpha
Classifier: License :: OSI Approved :: BSD License
Classifier: Operating System :: OS Independent
Requires-Python: >=3.6
License-File: LICENSE
Requires-Dist: numpy
Requires-Dist: cmocean
Requires-Dist: matplotlib
